Metadata-Version: 2.1
Name: version-wizard
Version: 0.1.2
Home-page: https://github.com/tillahoffmann/wizard-version/
Author: Till Hoffmann
Provides-Extra: doc
Provides-Extra: test
License-File: LICENSE
